odoo/addons/ssi_hr_employee_stock/README.rst
odoo/addons/ssi_hr_employee_stock/__init__.py
odoo/addons/ssi_hr_employee_stock/__manifest__.py
odoo/addons/ssi_hr_employee_stock/data/location_type_data.xml
odoo/addons/ssi_hr_employee_stock/models/__init__.py
odoo/addons/ssi_hr_employee_stock/models/hr_employee.py
odoo/addons/ssi_hr_employee_stock/static/description/icon.png
odoo/addons/ssi_hr_employee_stock/views/hr_employee_views.xml
odoo14_addon_ssi_hr_employee_stock-14.0.1.3.0.dist-info/METADATA
odoo14_addon_ssi_hr_employee_stock-14.0.1.3.0.dist-info/WHEEL
odoo14_addon_ssi_hr_employee_stock-14.0.1.3.0.dist-info/top_level.txt
odoo14_addon_ssi_hr_employee_stock-14.0.1.3.0.dist-info/RECORD
